curvestat/__init__.py
curvestat/metadata.py
curvestat/stats.py
curvestat/tests/__init__.py
curvestat/tests/curvestat_tests.py
curvestat-0.0.1.dist-info/LICENSE
curvestat-0.0.1.dist-info/METADATA
curvestat-0.0.1.dist-info/WHEEL
curvestat-0.0.1.dist-info/top_level.txt
curvestat-0.0.1.dist-info/RECORD
